{
  "entity": "weak",
  "timestamp": "2025-05-06T21:16:21.178152",
  "risk_summary": {
    "financial": "Low",
    "operational": "High",
    "market": "Medium",
    "overall": "High",
    "reasoning": "The knowledge graph primarily highlights repeated operational issues at ManufactureX concerning supply chain disruptions. This indicates a significant operational risk. There are no explicit financial or market risks mentioned, so their scores reflect lower risk levels. The overall risk is moderate due to the operational challenges and lack of direct financial or market impacts."
  },
  "strategies": [
    {
      "title": "Supplier Diversification Initiative",
      "rationale": "The current reliance on a single supplier increases operational risk. By diversifying suppliers, we can mitigate supply chain disruptions and achieve cost savings.",
      "benefits": [
        "Reduce supply chain disruption risks",
        "Achieve cost savings"
      ],
      "implementation_steps": [
        "Identify and vet alternative suppliers",
        "Negotiate contracts with new suppliers to secure better terms",
        "Implement a supplier management system"
      ],
      "kpis": [
        "Number of new suppliers sourced",
        "Cost reduction achieved through diversification"
      ],
      "timeline": "medium",
      "priority": "high"
    },
    {
      "title": "Customer Acquisition Cost Optimization Program",
      "rationale": "High customer acquisition costs indicate inefficiencies in marketing strategies. By adopting targeted marketing approaches, we can reduce CAC and improve ROI.",
      "benefits": [
        "Lower customer acquisition cost",
        "Improved return on investment for marketing"
      ],
      "implementation_steps": [
        "Utilize data analytics to identify high-value customer segments",
        "Implement targeted marketing campaigns focusing on those segments",
        "A/B test different campaign strategies"
      ],
      "kpis": [
        "Customer acquisition cost reduction ratio",
        "Marketing campaign ROI improvement percentage"
      ],
      "timeline": "short",
      "priority": "high"
    },
    {
      "title": "Process Automation for Design Win Optimization",
      "rationale": "The entity's high number of design wins suggests a need to standardize and automate processes in product development. This will increase efficiency and accelerate time-to-market.",
      "benefits": [
        "Increase design win conversion rates",
        "Accelerate time-to-market"
      ],
      "implementation_steps": [
        "Implement design thinking workshops across departments",
        "Develop standardized workflows for product development",
        "Leverage digital tools for collaboration"
      ],
      "kpis": [
        "Design win conversion rate improvement",
        "Time-to-market reduction"
      ],
      "timeline": "medium",
      "priority": "high"
    },
    {
      "title": "Product Line Expansion Strategy",
      "rationale": "The entity's high annual recurring revenue indicates a strong base, but to grow further, expanding the product line can capture new markets and increase ARRV.",
      "benefits": [
        "Expand market reach",
        "Increase annual recurring revenue"
      ],
      "implementation_steps": [
        "Conduct market research to identify adjacent markets",
        "Develop new products based on existing design wins",
        "Test new products in beta phases"
      ],
      "kpis": [
        "New product line launch success rate",
        "Annual recurring revenue growth percentage"
      ],
      "timeline": "long",
      "priority": "high"
    },
    {
      "title": "Real-time Monitoring System Implementation",
      "rationale": "The entity's high operational risk suggests a need for better oversight. Implementing real-time monitoring will allow for faster issue resolution and improved operational efficiency.",
      "benefits": [
        "Reduce operational downtime",
        "Improve process visibility"
      ],
      "implementation_steps": [
        "Install IoT sensors across production lines",
        "Develop a real-time monitoring dashboard",
        "Train staff on how to use the system"
      ],
      "kpis": [
        "Operational downtime reduction percentage",
        "Average time to resolve issues"
      ],
      "timeline": "short",
      "priority": "high"
    }
  ],
  "visualization_data": {
    "strategy_prioritization": {
      "type": "bubble_chart",
      "description": "Strategy prioritization by impact, effort, and priority",
      "data": [
        {
          "title": "Supplier Diversification Initiative",
          "impact": 0.6,
          "effort": 0.6,
          "priority": "high",
          "size": 50
        },
        {
          "title": "Customer Acquisition Cost Optimization Program",
          "impact": 0.7999999999999999,
          "effort": 0.8999999999999999,
          "priority": "high",
          "size": 50
        },
        {
          "title": "Process Automation for Design Win Optimization",
          "impact": 0.95,
          "effort": 0.3,
          "priority": "high",
          "size": 50
        },
        {
          "title": "Product Line Expansion Strategy",
          "impact": 0.6,
          "effort": 0.6,
          "priority": "high",
          "size": 50
        },
        {
          "title": "Real-time Monitoring System Implementation",
          "impact": 0.7999999999999999,
          "effort": 0.8999999999999999,
          "priority": "high",
          "size": 50
        }
      ]
    },
    "implementation_timeline": {
      "type": "gantt_chart",
      "description": "Implementation timeline for recommended strategies",
      "data": [
        {
          "title": "Supplier Diversification Initiative",
          "start_days": 0,
          "end_days": 180,
          "priority": "high",
          "group": 0
        },
        {
          "title": "Customer Acquisition Cost Optimization Program",
          "start_days": 90,
          "end_days": 180,
          "priority": "high",
          "group": 0
        },
        {
          "title": "Process Automation for Design Win Optimization",
          "start_days": 135,
          "end_days": 315,
          "priority": "high",
          "group": 1
        },
        {
          "title": "Product Line Expansion Strategy",
          "start_days": 225,
          "end_days": 590,
          "priority": "high",
          "group": 1
        },
        {
          "title": "Real-time Monitoring System Implementation",
          "start_days": 407,
          "end_days": 497,
          "priority": "high",
          "group": 2
        }
      ]
    },
    "risk_mitigation_impact": {
      "type": "radar_chart",
      "description": "Expected risk reduction by category",
      "categories": [
        "Financial",
        "Operational",
        "Market",
        "Reputational",
        "Legal"
      ],
      "datasets": [
        {
          "label": "Supplier Diversification Initiative",
          "data": [
            0.30000000000000004,
            0.30000000000000004,
            0.1,
            0.1,
            0.20000000000000004
          ]
        },
        {
          "label": "Customer Acquisition Cost Optimization Program",
          "data": [
            0.4,
            0.4,
            0.4,
            0.30000000000000004,
            0.1
          ]
        },
        {
          "label": "Process Automation for Design Win Optimization",
          "data": [
            0.2,
            0.5,
            0.5,
            0.2,
            0.2
          ]
        },
        {
          "label": "Product Line Expansion Strategy",
          "data": [
            0.30000000000000004,
            0.30000000000000004,
            0.30000000000000004,
            0.1,
            0.1
          ]
        },
        {
          "label": "Real-time Monitoring System Implementation",
          "data": [
            0.1,
            0.4,
            0.1,
            0.1,
            0.30000000000000004
          ]
        }
      ]
    },
    "financial_impact": {
      "type": "bar_chart",
      "description": "Projected financial impact of strategies",
      "labels": [
        "Supplier Diversification Initiative",
        "Customer Acquisition Cost Optimization Program",
        "Process Automation for Design Win Optimization",
        "Product Line Expansion Strategy",
        "Real-time Monitoring System Implementation"
      ],
      "datasets": [
        {
          "label": "Revenue Impact (%)",
          "data": [
            5.0,
            6.0,
            7.0,
            7.0,
            6.0
          ]
        },
        {
          "label": "Cost Savings (%)",
          "data": [
            4.0,
            5.0,
            3.0,
            6.0,
            5.0
          ]
        }
      ]
    }
  },
  "strategic_opportunities": {
    "partnership_opportunities": [],
    "market_expansion_opportunities": []
  }
}